neutron/__init__.py
neutron/_i18n.py
neutron/auth.py
neutron/manager.py
neutron/neutron_plugin_base_v2.py
neutron/opts.py
neutron/policy.py
neutron/service.py
neutron/version.py
neutron/worker.py
neutron/wsgi.py
neutron/agent/__init__.py
neutron/agent/agent_extensions_manager.py
neutron/agent/dhcp_agent.py
neutron/agent/firewall.py
neutron/agent/l3_agent.py
neutron/agent/metadata_agent.py
neutron/agent/resource_cache.py
neutron/agent/rpc.py
neutron/agent/securitygroups_rpc.py
neutron/agent/common/__init__.py
neutron/agent/common/async_process.py
neutron/agent/common/base_polling.py
neutron/agent/common/ip_lib.py
neutron/agent/common/ovs_lib.py
neutron/agent/common/ovsdb_monitor.py
neutron/agent/common/placement_report.py
neutron/agent/common/polling.py
neutron/agent/common/resource_processing_queue.py
neutron/agent/common/utils.py
neutron/agent/dhcp/__init__.py
neutron/agent/dhcp/agent.py
neutron/agent/l2/__init__.py
neutron/agent/l2/l2_agent_extensions_manager.py
neutron/agent/l2/extensions/__init__.py
neutron/agent/l2/extensions/fdb_population.py
neutron/agent/l2/extensions/qos.py
neutron/agent/l2/extensions/qos_linux.py
neutron/agent/l2/extensions/dhcp/__init__.py
neutron/agent/l2/extensions/dhcp/base.py
neutron/agent/l3/__init__.py
neutron/agent/l3/agent.py
neutron/agent/l3/dvr.py
neutron/agent/l3/dvr_edge_ha_router.py
neutron/agent/l3/dvr_edge_router.py
neutron/agent/l3/dvr_fip_ns.py
neutron/agent/l3/dvr_local_router.py
neutron/agent/l3/dvr_router_base.py
neutron/agent/l3/dvr_snat_ns.py
neutron/agent/l3/fip_rule_priority_allocator.py
neutron/agent/l3/ha.py
neutron/agent/l3/ha_router.py
neutron/agent/l3/item_allocator.py
neutron/agent/l3/keepalived_state_change.py
neutron/agent/l3/l3_agent_extension_api.py
neutron/agent/l3/l3_agent_extensions_manager.py
neutron/agent/l3/legacy_router.py
neutron/agent/l3/link_local_allocator.py
neutron/agent/l3/namespace_manager.py
neutron/agent/l3/namespaces.py
neutron/agent/l3/router_info.py
neutron-18.6.0.dist-info/AUTHORS
neutron-18.6.0.dist-info/LICENSE
neutron-18.6.0.dist-info/METADATA
neutron-18.6.0.dist-info/WHEEL
neutron-18.6.0.dist-info/entry_points.txt
neutron-18.6.0.dist-info/pbr.json
neutron-18.6.0.dist-info/top_level.txt
neutron-18.6.0.dist-info/RECORD
